<?xml version="1.0" encoding="utf-8" ?>
<dwsync>
<file name="adry.jpg" server="ftp.adry.ro//public_html/" local="129518401401250000" remote="129595154400000000" />
<file name="girl_1.jpg" server="ftp.adry.ro//public_html/" local="129518408720000000" remote="129595154400000000" />
<file name="girl_2.jpg" server="ftp.adry.ro//public_html/" local="129518407220156250" remote="129595154400000000" />
<file name="girl_3.jpg" server="ftp.adry.ro//public_html/" local="129518409712968750" remote="129595154400000000" />
<file name="girl_4.jpg" server="ftp.adry.ro//public_html/" local="129518405960312500" remote="129595154400000000" />
<file name="girl_5.jpg" server="ftp.adry.ro//public_html/" local="129518412406093750" remote="129595154400000000" />
<file name="men_1.jpg" server="ftp.adry.ro//public_html/" local="129518405111562500" remote="129595154400000000" />
<file name="men_2.jpg" server="ftp.adry.ro//public_html/" local="129518410612500000" remote="129595154400000000" />
<file name="men_3.jpg" server="ftp.adry.ro//public_html/" local="129518411240468750" remote="129595154400000000" />
<file name="men_4.jpg" server="ftp.adry.ro//public_html/" local="129518411893593750" remote="129595154400000000" />
<file name="men_5.jpg" server="ftp.adry.ro//public_html/" local="129518403761875000" remote="129595154400000000" />
<file name="men_6.jpg" server="ftp.adry.ro//public_html/" local="129518402727187500" remote="129595154400000000" />
<file name="girl_10.jpg" server="ftp.adry.ro//public_html/" local="129533057224218750" remote="129595154400000000" />
<file name="girl_6.jpg" server="ftp.adry.ro//public_html/" local="129533036070781250" remote="129595154400000000" />
<file name="girl_7.jpg" server="ftp.adry.ro//public_html/" local="129533037614062500" remote="129595154400000000" />
<file name="girl_8.jpg" server="ftp.adry.ro//public_html/" local="129533048585312500" remote="129595154400000000" />
<file name="girl_9.jpg" server="ftp.adry.ro//public_html/" local="129533055695625000" remote="129595154400000000" />
<file name="men_10.jpg" server="ftp.adry.ro//public_html/" local="129533058239687500" remote="129595154400000000" />
<file name="men_11.jpg" server="ftp.adry.ro//public_html/" local="129533047329531250" remote="129595154400000000" />
<file name="men_12.jpg" server="ftp.adry.ro//public_html/" local="129533056120000000" remote="129595154400000000" />
<file name="men_13.jpg" server="ftp.adry.ro//public_html/" local="129533056484218750" remote="129595154400000000" />
<file name="men_14.jpg" server="ftp.adry.ro//public_html/" local="129533056894843750" remote="129595154400000000" />
<file name="men_15.jpg" server="ftp.adry.ro//public_html/" local="129533057664687500" remote="129595154400000000" />
<file name="men_16.jpg" server="ftp.adry.ro//public_html/" local="129533058041406250" remote="129595154400000000" />
<file name="men_7.jpg" server="ftp.adry.ro//public_html/" local="129533030593437500" remote="129595154400000000" />
<file name="men_8.jpg" server="ftp.adry.ro//public_html/" local="129533031513437500" remote="129595154400000000" />
<file name="men_9.jpg" server="ftp.adry.ro//public_html/" local="129533039618906250" remote="129595154400000000" />
<file name="men_17.jpg" server="ftp.adry.ro//public_html/" local="129591178674218750" remote="129595154400000000" />
<file name="men_18.jpg" server="ftp.adry.ro//public_html/" local="129591843843281250" remote="129595154400000000" />
<file name="adry.jpg" server="ftp.loghin.com//" local="129518401401250000" remote="129601975800000000" />
<file name="girl_1.jpg" server="ftp.loghin.com//" local="129518408720000000" remote="129601975800000000" />
<file name="girl_10.jpg" server="ftp.loghin.com//" local="129533057224218750" remote="129601975800000000" />
<file name="girl_2.jpg" server="ftp.loghin.com//" local="129518407220156250" remote="129601975800000000" />
<file name="girl_3.jpg" server="ftp.loghin.com//" local="129518409712968750" remote="129601975800000000" />
<file name="girl_4.jpg" server="ftp.loghin.com//" local="129518405960312500" remote="129601975800000000" />
<file name="girl_5.jpg" server="ftp.loghin.com//" local="129518412406093750" remote="129601975800000000" />
<file name="girl_6.jpg" server="ftp.loghin.com//" local="129533036070781250" remote="129601975800000000" />
<file name="girl_7.jpg" server="ftp.loghin.com//" local="129533037614062500" remote="129601975800000000" />
<file name="girl_8.jpg" server="ftp.loghin.com//" local="129533048585312500" remote="129601975800000000" />
<file name="girl_9.jpg" server="ftp.loghin.com//" local="129533055695625000" remote="129601975800000000" />
<file name="men_1.jpg" server="ftp.loghin.com//" local="129518405111562500" remote="129601975800000000" />
<file name="men_10.jpg" server="ftp.loghin.com//" local="129533058239687500" remote="129601975800000000" />
<file name="men_11.jpg" server="ftp.loghin.com//" local="129533047329531250" remote="129601975800000000" />
<file name="men_12.jpg" server="ftp.loghin.com//" local="129533056120000000" remote="129601975800000000" />
<file name="men_13.jpg" server="ftp.loghin.com//" local="129533056484218750" remote="129601975800000000" />
<file name="men_14.jpg" server="ftp.loghin.com//" local="129533056894843750" remote="129601975800000000" />
<file name="men_15.jpg" server="ftp.loghin.com//" local="129533057664687500" remote="129601975800000000" />
<file name="men_16.jpg" server="ftp.loghin.com//" local="129533058041406250" remote="129601975800000000" />
<file name="men_17.jpg" server="ftp.loghin.com//" local="129591178674218750" remote="129601975800000000" />
<file name="men_18.jpg" server="ftp.loghin.com//" local="129591843843281250" remote="129601975800000000" />
<file name="men_2.jpg" server="ftp.loghin.com//" local="129518410612500000" remote="129601975800000000" />
<file name="men_3.jpg" server="ftp.loghin.com//" local="129518411240468750" remote="129601975800000000" />
<file name="men_4.jpg" server="ftp.loghin.com//" local="129518411893593750" remote="129601975800000000" />
<file name="men_5.jpg" server="ftp.loghin.com//" local="129518403761875000" remote="129601975800000000" />
<file name="men_6.jpg" server="ftp.loghin.com//" local="129518402727187500" remote="129601975800000000" />
<file name="men_7.jpg" server="ftp.loghin.com//" local="129533030593437500" remote="129601975800000000" />
<file name="men_8.jpg" server="ftp.loghin.com//" local="129533031513437500" remote="129601975800000000" />
<file name="men_9.jpg" server="ftp.loghin.com//" local="129533039618906250" remote="129601975800000000" />
</dwsync>